application_example/__init__.py
application_example/example.py
keepcodingtest_jeanflores-0.0.1.dist-info/METADATA
keepcodingtest_jeanflores-0.0.1.dist-info/WHEEL
keepcodingtest_jeanflores-0.0.1.dist-info/top_level.txt
keepcodingtest_jeanflores-0.0.1.dist-info/RECORD
