Metadata-Version: 2.1
Name: keepcodingtest-jeanflores
Version: 0.0.1
Summary: un ejemplo de prueba
Author: keepcoder_jeanflores
Author-email: keepcodingjeanflores@gmail.com
License: UNKNOWN
Platform: UNKNOWN
Requires-Python: >=3.9
Requires-Dist: build
Requires-Dist: twine
